example_package_mxgnxs/__init__.py
example_package_mxgnxs/example.py
example_package_mxgnxs-0.1.0.dist-info/LICENSE
example_package_mxgnxs-0.1.0.dist-info/METADATA
example_package_mxgnxs-0.1.0.dist-info/WHEEL
example_package_mxgnxs-0.1.0.dist-info/top_level.txt
example_package_mxgnxs-0.1.0.dist-info/RECORD
