Metadata-Version: 2.1
Name: example_package_mxgnxs
Version: 0.1.0
Summary: Simple test project
Home-page: https://github.com/CMM02/python-publishing
Author: Carl Magnus Meier
Author-email: magnus.meier@outook.de
Classifier: Programming Language :: Python :: 3
Classifier: License :: OSI Approved :: MIT License
Classifier: Operating System :: OS Independent
Requires-Python: >=3.8
License-File: LICENSE
